LICENSE
MANIFEST.in
setup.py
chat_exporter/__init__.py
chat_exporter/chat_exporter.py
chat_exporter/emoji_convert.py
chat_exporter/markdown_convert.py
chat_exporter/mention_convert.py
chat_exporter/misc_tools.py
chat_exporter/chat_exporter_html/__init__.py
chat_exporter/chat_exporter_html/base.html
chat_exporter/chat_exporter_html/bot-tag.html
chat_exporter/chat_exporter_html/continue_message.html
chat_exporter/chat_exporter_html/custom_emoji_attachment.html
chat_exporter/chat_exporter_html/embed_author.html
chat_exporter/chat_exporter_html/embed_author_icon.html
chat_exporter/chat_exporter_html/embed_footer.html
chat_exporter/chat_exporter_html/embed_footer_image.html
chat_exporter/chat_exporter_html/embed_image.html
chat_exporter/chat_exporter_html/embed_thumbnail.html
chat_exporter/chat_exporter_html/emoji_attachment.html
chat_exporter/chat_exporter_html/end_message.html
chat_exporter/chat_exporter_html/image-attachment.html
chat_exporter/chat_exporter_html/message-embed-field-inline.html
chat_exporter/chat_exporter_html/message-embed-field.html
chat_exporter/chat_exporter_html/message-embed.html
chat_exporter/chat_exporter_html/message.html
chat_exporter/chat_exporter_html/message_attachment.html
enhanced_chat_exporter.egg-info/PKG-INFO
enhanced_chat_exporter.egg-info/SOURCES.txt
enhanced_chat_exporter.egg-info/dependency_links.txt
enhanced_chat_exporter.egg-info/requires.txt
enhanced_chat_exporter.egg-info/top_level.txt